{
    "id": "41320695",
    "登記機關": "高雄市政府",
    "核准設立日期": {
        "year": 2015,
        "month": 6,
        "day": 23
    },
    "最近異動日期": {
        "year": 2025,
        "month": 2,
        "day": 18
    },
    "商業名稱": "吉鑫小吃店",
    "負責人姓名": "陳_柔",
    "資本額(元)": "30,000",
    "組織類型": "獨資",
    "地址": "高雄市鼓山區九如四路１０３８號１樓",
    "營業項目": "1\r\n\t\t\t\t\t\t\t\t\t\t\t\t\t\t\tF501060\r\n\t\t\t\t\t\t\t\t\t\t\t\t\t\t\t餐館業",
    "出資額(元)": {
        "陳_柔": "30000"
    },
    "url": "\/fts\/query\/QueryBusmDetail\/queryBusmDetail.do?objectId=SEI0MTMyMDY5NTMwMjAwMDAwMDAwMDExNzY2NjYz&banNo=41320695&banKey=30200000000011766663&disj=7542307A78BE3A1CA89224A0E7734490&fhl=zh_TW",
    "登記現況": "核准設立"
}