{
    "id": "45861221",
    "登記機關": "臺中市政府",
    "核准設立日期": {
        "year": 2010,
        "month": 7,
        "day": 14
    },
    "最近異動日期": {
        "year": 2024,
        "month": 7,
        "day": 5
    },
    "商業名稱": "東方人文工作室",
    "負責人姓名": "李_珍",
    "資本額(元)": "200,000",
    "組織類型": "獨資",
    "地址": "臺中市南屯區春安里春安路70號3樓之1",
    "營業項目": "1\r\n\t\t\t\t\t\t\t\t\t\t\t\t\t\t\tJZ99050\r\n\t\t\t\t\t\t\t\t\t\t\t\t\t\t\t仲介服務業\r\n\t\t\t\t\t\t\t\t\t\t\t\t\t\t\r\n\t\t\t\t\t\t\t\t\t\t\t\t\t\t\t2\r\n\t\t\t\t\t\t\t\t\t\t\t\t\t\t\tI503010\r\n\t\t\t\t\t\t\t\t\t\t\t\t\t\t\t景觀、室內設計業\r\n\t\t\t\t\t\t\t\t\t\t\t\t\t\t\r\n\t\t\t\t\t\t\t\t\t\t\t\t\t\t\t3\r\n\t\t\t\t\t\t\t\t\t\t\t\t\t\t\tI501010\r\n\t\t\t\t\t\t\t\t\t\t\t\t\t\t\t產品設計業\r\n\t\t\t\t\t\t\t\t\t\t\t\t\t\t\r\n\t\t\t\t\t\t\t\t\t\t\t\t\t\t\t4\r\n\t\t\t\t\t\t\t\t\t\t\t\t\t\t\tI401010\r\n\t\t\t\t\t\t\t\t\t\t\t\t\t\t\t一般廣告服務業",
    "出資額(元)": {
        "李_珍": "200000"
    },
    "url": "\/fts\/query\/QueryBusmDetail\/queryBusmDetail.do?objectId=SEI0NTg2MTIyMTcxNzAwMDAwMDAwMDA1Mjk3ODcy&banNo=45861221&banKey=71700000000005297872&disj=F5FA1001713BEC3C806ED932FFD99AB6&fhl=zh_TW",
    "登記現況": "核准設立"
}