{
    "id": "48855645",
    "登記機關": "臺北市商業處",
    "核准設立日期": {
        "year": 2007,
        "month": 2,
        "day": 2
    },
    "最近異動日期": {
        "year": 2020,
        "month": 2,
        "day": 3
    },
    "商業名稱": "森麒企業社",
    "負責人姓名": "江_玲",
    "現況": "歇業",
    "資本額(元)": "200,000",
    "組織類型": "獨資",
    "地址": "臺北市中山區民族東路258號3樓",
    "營業項目": "一、F102170食品什貨批發業二、F203010食品什貨、飲料零售業",
    "出資額(元)": {
        "江_玲": "200000"
    },
    "url": "\/fts\/query\/QueryBusmDetail\/queryBusmDetail.do?objectId=SEI0ODg1NTY0NTcwMTAwMDAwMDAwMDAwNDEyMDYz&banNo=48855645&banKey=70100000000000412063"
}