{
    "id": "92304873",
    "登記機關": "臺中市政府",
    "核准設立日期": {
        "year": 2023,
        "month": 3,
        "day": 10
    },
    "最近異動日期": {
        "year": 2024,
        "month": 6,
        "day": 13
    },
    "商業名稱": "后里浪人鐵板燒",
    "負責人姓名": "陳_熹",
    "資本額(元)": "120,000",
    "組織類型": "合夥",
    "地址": "臺中市后里區墩北里四村路99號1樓",
    "營業項目": "1\r\n\t\t\t\t\t\t\t\t\t\t\t\t\t\t\tF501060\r\n\t\t\t\t\t\t\t\t\t\t\t\t\t\t\t餐館業\r\n\t\t\t\t\t\t\t\t\t\t\t\t\t\t\r\n\t\t\t\t\t\t\t\t\t\t\t\t\t\t\t2\r\n\t\t\t\t\t\t\t\t\t\t\t\t\t\t\tF399040\r\n\t\t\t\t\t\t\t\t\t\t\t\t\t\t\t無店面零售業",
    "合夥人姓名": "陳宥臣",
    "出資額(元)": {
        "陳_熹": "60000",
        "陳_臣": "60000"
    },
    "url": "\/fts\/query\/QueryBusmDetail\/queryBusmDetail.do?objectId=SEI5MjMwNDg3MzkxNzAwMDAwMDAwMDIyNDAzOTAw&banNo=92304873&banKey=91700000000022403900&disj=43EC558649C7E25D93E200EDECC23EED&fhl=zh_TW",
    "登記現況": "歇業"
}