{
    "id": "92353727",
    "登記機關": "臺南市政府",
    "核准設立日期": {
        "year": 2023,
        "month": 4,
        "day": 10
    },
    "最近異動日期": {
        "year": 2024,
        "month": 8,
        "day": 21
    },
    "商業名稱": "東旭磁磚設計",
    "負責人姓名": "楊_憲",
    "資本額(元)": "169,000",
    "組織類型": "獨資",
    "地址": "臺南市善化區胡厝里百二甲13之5號",
    "營業項目": "1\r\n\t\t\t\t\t\t\t\t\t\t\t\t\t\t\tEZ99990\r\n\t\t\t\t\t\t\t\t\t\t\t\t\t\t\t其他工程業\r\n\t\t\t\t\t\t\t\t\t\t\t\t\t\t\r\n\t\t\t\t\t\t\t\t\t\t\t\t\t\t\t2\r\n\t\t\t\t\t\t\t\t\t\t\t\t\t\t\tF111090\r\n\t\t\t\t\t\t\t\t\t\t\t\t\t\t\t建材批發業\r\n\t\t\t\t\t\t\t\t\t\t\t\t\t\t\r\n\t\t\t\t\t\t\t\t\t\t\t\t\t\t\t3\r\n\t\t\t\t\t\t\t\t\t\t\t\t\t\t\tI503010\r\n\t\t\t\t\t\t\t\t\t\t\t\t\t\t\t景觀、室內設計業\r\n\t\t\t\t\t\t\t\t\t\t\t\t\t\t\r\n\t\t\t\t\t\t\t\t\t\t\t\t\t\t\t4\r\n\t\t\t\t\t\t\t\t\t\t\t\t\t\t\tZZ99999\r\n\t\t\t\t\t\t\t\t\t\t\t\t\t\t\t除許可業務外，得經營法令非禁止或限制之業務",
    "出資額(元)": {
        "楊_憲": "169000"
    },
    "url": "\/fts\/query\/QueryBusmDetail\/queryBusmDetail.do?objectId=SEI5MjM1MzcyNzYyMTAwMDAwMDAwMDIyNTI4ODk4&banNo=92353727&banKey=62100000000022528898&disj=07B69BAE2FAA105A3C80DEFC0158363A&fhl=zh_TW",
    "登記現況": "歇業"
}