{
    "id": "92908732",
    "登記機關": "新北市政府",
    "核准設立日期": {
        "year": 1995,
        "month": 6,
        "day": 19
    },
    "商業名稱": "佑成工程行",
    "負責人姓名": "楊_根",
    "現況": "歇業／撤銷",
    "資本額(元)": "100,000",
    "組織類型": "獨資",
    "地址": "新北市中和區興南路１段１５３之２號︵３樓︶",
    "營業項目": "１、室內裝潢設計施工工程油漆工程承包業務及其材料之買賣批發業務︵營造業務除外︶︵建築師業除外︶︵現場僅供辦公室使用︶２、燈飾建材五金衛浴設備及其材料之批發業務３、模板砂石水泥之買賣批發業務︵現場不堆置︶４、庭園綠化設計施工及景觀設計施工及其材料之批發業務︵營造業及土木包工業除外︶︵現場僅供辦公室使用︶。",
    "出資額(元)": {
        "楊_根": "100000"
    },
    "異動核准日期": {
        "year": 2018,
        "month": 8,
        "day": 30
    }
}