{
    "id": "93194852",
    "登記機關": "臺北市商業處",
    "核准設立日期": {
        "year": 2024,
        "month": 8,
        "day": 12
    },
    "最近異動日期": {
        "year": 2024,
        "month": 8,
        "day": 12
    },
    "商業名稱": "緣宏益企業社",
    "負責人姓名": "趙_益",
    "資本額(元)": "188,000",
    "組織類型": "獨資",
    "地址": "臺北市大同區重慶北路3段335巷35號1樓",
    "營業項目": "一、F203010食品什貨、飲料零售業",
    "出資額(元)": {
        "趙_益": "188000"
    },
    "url": "\/fts\/query\/QueryBusmDetail\/queryBusmDetail.do?objectId=SEI5MzE5NDg1MjIwMTAwMDAwMDAwMDI0NjYxOTIy&banNo=93194852&banKey=20100000000024661922&disj=C2CFC11EFBD07DA3515FB8E688DF18F7&fhl=zh_TW",
    "登記現況": "核准設立"
}