{
    "id": "94949371",
    "登記機關": "桃園市政府",
    "核准設立日期": {
        "year": 2003,
        "month": 6,
        "day": 3
    },
    "最近異動日期": {
        "year": 2025,
        "month": 4,
        "day": 9
    },
    "商業名稱": "福多多彩券行",
    "負責人姓名": "葉_禎",
    "資本額(元)": "100,000",
    "組織類型": "獨資",
    "地址": "桃園市桃園區同安里新埔六街126號1樓",
    "營業項目": "一、IZ14020公益彩券經銷業",
    "出資額(元)": {
        "葉_禎": "100000"
    },
    "url": "\/fts\/query\/QueryBusmDetail\/queryBusmDetail.do?objectId=SEI5NDk0OTM3MTYzMjAwMDAwMDAwMDAwMzM3MjQy&banNo=94949371&banKey=63200000000000337242&disj=AA7388B2E2A4650D05655FFFE0EC7171&fhl=zh_TW",
    "登記現況": "核准設立"
}