{
    "id": "95014763",
    "登記機關": "桃園市政府",
    "核准設立日期": {
        "year": 2024,
        "month": 4,
        "day": 25
    },
    "最近異動日期": {
        "year": 2024,
        "month": 10,
        "day": 16
    },
    "商業名稱": "食和精緻盒餐",
    "負責人姓名": "邱_頡",
    "資本額(元)": "200,000",
    "組織類型": "獨資",
    "地址": "桃園市龜山區文化里復興三路3之1號",
    "營業項目": "一、F501060餐館業二、F203010食品什貨、飲料零售業",
    "出資額(元)": {
        "邱_頡": "200000"
    },
    "url": "\/fts\/query\/QueryBusmDetail\/queryBusmDetail.do?objectId=SEI5NTAxNDc2MzEzMjAwMDAwMDAwMDI0MTg2Mjk2&banNo=95014763&banKey=13200000000024186296&disj=9945CD0EA8381F8F30ADD2CC6DAF162B&fhl=zh_TW",
    "登記現況": "核准設立"
}