{
    "id": "96677542",
    "登記機關": "澎湖縣政府",
    "核准設立日期": {
        "year": 1990,
        "month": 6,
        "day": 8
    },
    "最近異動日期": {
        "year": 2023,
        "month": 9,
        "day": 20
    },
    "商業名稱": "大成號",
    "負責人姓名": "廖_咪",
    "現況": "歇業",
    "資本額(元)": "3,000",
    "組織類型": "獨資",
    "地址": "澎湖縣湖西鄉隘門村３７–１號１樓",
    "營業項目": "什貨買賣。麵條製造。",
    "出資額(元)": {
        "廖_咪": "3000"
    },
    "url": "\/fts\/query\/QueryBusmDetail\/queryBusmDetail.do?objectId=SEI5NjY3NzU0MjA0NDAwMDAwMDAwMDAwMDE0MDc2&banNo=96677542&banKey=04400000000000014076&disj=BF7548FBC2F611223DEFC1DC7ED2E5E5&fhl=zh_TW"
}