{
    "id": "97562435",
    "登記機關": "臺中市政府",
    "核准設立日期": {
        "year": 2018,
        "month": 6,
        "day": 8
    },
    "最近異動日期": {
        "year": 2024,
        "month": 12,
        "day": 30
    },
    "商業名稱": "億昌特殊網版印刷廠",
    "負責人姓名": "王_旺",
    "資本額(元)": "3,000,000",
    "組織類型": "合夥",
    "地址": "臺中市太平區新高里樹德路１６之５號１樓",
    "營業項目": "1\r\n\t\t\t\t\t\t\t\t\t\t\t\t\t\t\tC701010\r\n\t\t\t\t\t\t\t\t\t\t\t\t\t\t\t印刷業",
    "合夥人姓名": [
        "王育靖",
        "王詠銘",
        "蕭玉"
    ],
    "出資額(元)": {
        "王_旺": "414000",
        "王_靖": "862000",
        "王_銘": "862000",
        "蕭_玉": "862000"
    },
    "url": "\/fts\/query\/QueryBusmDetail\/queryBusmDetail.do?objectId=SEI5NzU2MjQzNTMxNzAwMDAwMDAwMDE1NjkwMzY2&banNo=97562435&banKey=31700000000015690366&disj=D680CAC72C7A5D59D9A3237833847780&fhl=zh_TW",
    "登記現況": "歇業"
}