{
    "id": "98100741",
    "登記機關": "基隆市政府",
    "核准設立日期": {
        "year": 1997,
        "month": 4,
        "day": 3
    },
    "最近異動日期": {
        "year": 2022,
        "month": 8,
        "day": 18
    },
    "商業名稱": "和平商行",
    "負責人姓名": "曾_鳳",
    "現況": "歇業",
    "資本額(元)": "7,000",
    "組織類型": "獨資",
    "地址": "基隆市中正區和一路五八巷五八號一樓",
    "營業項目": "雜貨菸酒買賣。以下空白",
    "出資額(元)": {
        "曾_鳳": "7000"
    },
    "url": "\/fts\/query\/QueryBusmDetail\/queryBusmDetail.do?objectId=SEI5ODEwMDc0MTgxMTAwMDAwMDAwMDAwMDUyNTY0&banNo=98100741&banKey=81100000000000052564&disj=78807FEE5B122152E751A017DD0646C8&fhl=zh_TW"
}