{
    "id": "99532556",
    "登記機關": "高雄市政府",
    "核准設立日期": {
        "year": 2004,
        "month": 6,
        "day": 17
    },
    "最近異動日期": {
        "year": 2022,
        "month": 7,
        "day": 18
    },
    "商業名稱": "龍華旅館",
    "負責人姓名": "葉_馨",
    "現況": "核准設立",
    "資本額(元)": "3,000,000",
    "組織類型": "獨資",
    "地址": "高雄市旗山區三協里花旗二路３００巷２號１樓（等７２間）",
    "營業項目": "一、Ｊ９０１０２０一般旅館業二、Ｆ２０３０１０食品、飲料零售業（營業地址：旗山鎮三協里花旗二路３００巷２號、４號、６號、８號、１４號、１６號、１８號、２０號、２２號、２４號、２６號、２８號、３０號、３２號、３４號、３６號、３８號、４０號、４２號、４４號、４６號、４８號、５０號、５２號、５４號、５６號、５８號、６０號、６２號、６４號、６８號、７２號、７４號、７６號、７８號、８０號、８２號一樓及２之１號、４之１號、６之１號、８之１號、１０之１號、１２之１號、１４之１號、１６之１號、１８之１號、２２之１號、２４之１號、２６之１號、２８之１號、３２之１號、３４之１號、３６之１號、３８之１號、４０之１號、４４之１號、４６之１號、４８之１號、５０之１號、５２之１號、５４之１號、５６之１號、５８之１號、６４之１號、６８之１號、７０之１號、７２之１號、７４之１號、７６之１號、７８之１號、８０之１號、８２之１號二樓）",
    "出資額(元)": {
        "葉_馨": "3000000"
    },
    "url": "\/fts\/query\/QueryBusmDetail\/queryBusmDetail.do?objectId=SEI5OTUzMjU1Njg0MjAwMDAwMDAwMDAwMTY0NjI0&banNo=99532556&banKey=84200000000000164624&disj=5D287207BAE7A2B0DA9BB13900C5E7BF&fhl=zh_TW"
}