{
    "id": "99768356",
    "登記機關": "新北市政府",
    "核准設立日期": {
        "year": 2004,
        "month": 6,
        "day": 24
    },
    "最近異動日期": {
        "year": 2005,
        "month": 11,
        "day": 11
    },
    "商業名稱": "心光聯合行銷室",
    "負責人姓名": "藍_定",
    "現況": "撤銷",
    "資本額(元)": "200,000",
    "組織類型": "獨資",
    "地址": "新北市土城區永豐路１３５巷１７弄５號",
    "營業項目": "1\r\n\r\n                    F218010\r\n\r\n                    資訊軟體零售業\r\n\r\n              \r\n                    2\r\n\r\n                    F401010\r\n\r\n                    國際貿易業\r\n\r\n              \r\n                    3\r\n\r\n                    I103010\r\n\r\n                    企業經營管理顧問業\r\n\r\n              \r\n                    4\r\n\r\n                    F301030\r\n\r\n                    一般百貨業"
}