{
    "id": "99863160",
    "登記機關": "臺中市政府",
    "核准設立日期": {
        "year": 2004,
        "month": 6,
        "day": 30
    },
    "最近異動日期": {
        "year": 2017,
        "month": 2,
        "day": 16
    },
    "商業名稱": "聚益工程行",
    "負責人姓名": "謝_ ",
    "現況": "歇業／撤銷",
    "資本額(元)": "200,000",
    "組織類型": "獨資",
    "地址": "臺中市大里區大里里爽文路１２２號１樓",
    "營業項目": "1\n\r\n\t\t\t\t\t\t\tF111090\n\r\n\t\t\t\t\t\t\t建材批發業\n\r\n\t\t\t\t\t\t\r\n\t\t\t\t\t\t\t2\n\r\n\t\t\t\t\t\t\tE801010\n\r\n\t\t\t\t\t\t\t室內裝潢業（建築物室內裝修業務除外）\n\r\n\t\t\t\t\t\t\r\n\t\t\t\t\t\t\t3\n\r\n\t\t\t\t\t\t\tE801020\n\r\n\t\t\t\t\t\t\t門窗安裝工程業\n\r\n\t\t\t\t\t\t\r\n\t\t\t\t\t\t\t4\n\r\n\t\t\t\t\t\t\tE801030\n\r\n\t\t\t\t\t\t\t室內輕鋼架工程業\n\r\n\t\t\t\t\t\t\r\n\t\t\t\t\t\t\t5\n\r\n\t\t\t\t\t\t\tE801070\n\r\n\t\t\t\t\t\t\t廚具、衛浴設備安裝工程業\n\r\n\t\t\t\t\t\t\r\n\t\t\t\t\t\t\t6\n\r\n\t\t\t\t\t\t\tE901010\n\r\n\t\t\t\t\t\t\t油漆工程業\n\r\n\t\t\t\t\t\t\r\n\t\t\t\t\t\t\t7\n\r\n\t\t\t\t\t\t\tE903010\n\r\n\t\t\t\t\t\t\t防蝕、防銹工程業\n\r\n\t\t\t\t\t\t\r\n\t\t\t\t\t\t\t8\n\r\n\t\t\t\t\t\t\tEZ07010\n\r\n\t\t\t\t\t\t\t鑽孔工程業"
}