{
    "id": "72399936",
    "登記機關": "臺中市政府",
    "核准設立日期": {
        "year": 2017,
        "month": 4,
        "day": 6
    },
    "最近異動日期": {
        "year": 2020,
        "month": 7,
        "day": 22
    },
    "商業名稱": "肅肅叫小吃店",
    "負責人姓名": "石_芳",
    "現況": "歇業",
    "資本額(元)": "100,000",
    "組織類型": "獨資",
    "地址": "臺中市西屯區西平里文華路１２１之３號１樓",
    "營業項目": "1\r\n\t\t\t\t\t\t\t\t\t\t\t\t\t\t\tF501060\r\n\t\t\t\t\t\t\t\t\t\t\t\t\t\t\t餐館業",
    "出資額(元)": {
        "石_芳": "100000"
    },
    "url": "\/fts\/query\/QueryBusmDetail\/queryBusmDetail.do?objectId=SEI3MjM5OTkzNjUxNzAwMDAwMDAwMDE0MTY5MDk2&banNo=72399936&banKey=51700000000014169096&disj=A6C588D69F98D07FF31AE3FA83872C92"
}