{
    "id": "72548942",
    "登記機關": "臺中市政府",
    "核准設立日期": {
        "year": 2018,
        "month": 8,
        "day": 8
    },
    "最近異動日期": {
        "year": 2019,
        "month": 12,
        "day": 26
    },
    "商業名稱": "糸吉手作工作室",
    "負責人姓名": "曹_婕",
    "現況": "歇業",
    "資本額(元)": "30,000",
    "組織類型": "獨資",
    "地址": "臺中市太平區新福里新福路６０號十三樓",
    "營業項目": "1\r\n\t\t\t\t\t\t\t\t\t\t\t\t\t\t\tI501010\r\n\t\t\t\t\t\t\t\t\t\t\t\t\t\t\t產品設計業\r\n\t\t\t\t\t\t\t\t\t\t\t\t\t\t\r\n\t\t\t\t\t\t\t\t\t\t\t\t\t\t\t2\r\n\t\t\t\t\t\t\t\t\t\t\t\t\t\t\tI599990\r\n\t\t\t\t\t\t\t\t\t\t\t\t\t\t\t其他設計業\r\n\t\t\t\t\t\t\t\t\t\t\t\t\t\t\r\n\t\t\t\t\t\t\t\t\t\t\t\t\t\t\t3\r\n\t\t\t\t\t\t\t\t\t\t\t\t\t\t\tF399040\r\n\t\t\t\t\t\t\t\t\t\t\t\t\t\t\t無店面零售業\r\n\t\t\t\t\t\t\t\t\t\t\t\t\t\t\r\n\t\t\t\t\t\t\t\t\t\t\t\t\t\t\t4\r\n\t\t\t\t\t\t\t\t\t\t\t\t\t\t\tF399990\r\n\t\t\t\t\t\t\t\t\t\t\t\t\t\t\t其他綜合零售業",
    "出資額(元)": {
        "曹_婕": "30000"
    },
    "url": "\/fts\/query\/QueryBusmDetail\/queryBusmDetail.do?objectId=SEI3MjU0ODk0MjYxNzAwMDAwMDAwMDE1OTE3OTE4&banNo=72548942&banKey=61700000000015917918"
}