{
    "id": "73808874",
    "登記機關": "桃園縣政府",
    "核准設立日期": {
        "year": 1998,
        "month": 5,
        "day": 7
    },
    "最近異動日期": {
        "year": 2003,
        "month": 9,
        "day": 30
    },
    "商業名稱": "荔灣企業社",
    "負責人姓名": "林_銘",
    "現況": "歇業",
    "資本額(元)": "2,700,000",
    "組織類型": "獨資",
    "地址": "桃園縣中壢市東興里健行路１３０號３樓",
    "營業項目": "一、Ｆ１０１０２０蔬菜批發業二、Ｆ１０１０３０水果批發業三、Ｆ１０１０４０畜產品批發業四、Ｆ１０１０５０水產品批發業五、Ｆ１０２０１０冷凍食品批發業六、Ｆ１０２０４０飲料批發業七、Ｆ１０２０９０醃漬食品批發業（營業所在地限辦公室使用）（果菜魚類家畜等第一次批發交易應在市場內為之不得以拍賣仲介受託收取佣金等方式經營類似市場業務）"
}