{
    "id": "75154006",
    "登記機關": "高雄市政府",
    "核准設立日期": {
        "year": 1965,
        "month": 4,
        "day": 3
    },
    "最近異動日期": {
        "year": 2020,
        "month": 4,
        "day": 27
    },
    "商業名稱": "永樂計程汽車行",
    "負責人姓名": "蘇_勳",
    "現況": "核准設立",
    "資本額(元)": "4,200,000",
    "組織類型": "合夥",
    "地址": "高雄市三民區民族一路445之1號1樓",
    "營業項目": "1\r\n\t\t\t\t\t\t\t\t\t\t\t\t\t\t\tG101031\r\n\t\t\t\t\t\t\t\t\t\t\t\t\t\t\t計程車客運業\r\n\t\t\t\t\t\t\t\t\t\t\t\t\t\t\r\n\t\t\t\t\t\t\t\t\t\t\t\t\t\t\t2\r\n\t\t\t\t\t\t\t\t\t\t\t\t\t\t\tG201011\r\n\t\t\t\t\t\t\t\t\t\t\t\t\t\t\t計程車客運服務業",
    "合夥人姓名": "徐紹強",
    "出資額(元)": {
        "蘇_勳": "2200000",
        "徐_強": "2000000"
    },
    "url": "\/fts\/query\/QueryBusmDetail\/queryBusmDetail.do?objectId=SEI3NTE1NDAwNjkwMjAwMDAwMDAwMDAwMTU5MTQ1&banNo=75154006&banKey=90200000000000159145"
}