{
    "id": "75995227",
    "登記機關": "高雄市政府",
    "核准設立日期": {
        "year": 1979,
        "month": 12,
        "day": 6
    },
    "最近異動日期": {
        "year": 2020,
        "month": 11,
        "day": 30
    },
    "商業名稱": "雙桂商號",
    "負責人姓名": "趙_強",
    "現況": "核准設立",
    "資本額(元)": "5,000",
    "組織類型": "獨資",
    "地址": "高雄市三民區鼎金里鼎金後路４１巷３８號",
    "營業項目": "一菸酒及雜貨買賣．",
    "出資額(元)": {
        "趙_強": "5000"
    },
    "url": "\/fts\/query\/QueryBusmDetail\/queryBusmDetail.do?objectId=SEI3NTk5NTIyNzYwMjAwMDAwMDAwMDAwMTYyNzQy&banNo=75995227&banKey=60200000000000162742&disj=F9226DE779B081E58D2B540ACD1E5F81&fhl=zh_TW"
}