{
    "id": "79132103",
    "登記機關": "高雄市政府",
    "核准設立日期": {
        "year": 1966,
        "month": 12,
        "day": 19
    },
    "最近異動日期": {
        "year": 2019,
        "month": 11,
        "day": 15
    },
    "商業名稱": "新興理髮廳",
    "負責人姓名": "許_珠",
    "現況": "歇業",
    "資本額(元)": "8,000",
    "組織類型": "獨資",
    "地址": "高雄市鼓山區惠安里長安街１０之１號１樓",
    "營業項目": "理髮業．",
    "出資額(元)": {
        "許_珠": ""
    },
    "url": "\/fts\/query\/QueryBusmDetail\/queryBusmDetail.do?objectId=SEI3OTEzMjEwMzUwMjAwMDAwMDAwMDAwMTc3OTQx&banNo=79132103&banKey=50200000000000177941"
}