{
    "id": "31534830",
    "登記機關": "桃園市政府",
    "核准設立日期": {
        "year": 2011,
        "month": 9,
        "day": 21
    },
    "最近異動日期": {
        "year": 2023,
        "month": 10,
        "day": 16
    },
    "商業名稱": "龍武車業",
    "負責人姓名": "林_隆",
    "現況": "核准設立",
    "資本額(元)": "20,000",
    "組織類型": "獨資",
    "地址": "桃園市中壢區中正里榮安二街70號",
    "營業項目": "一、JA02020機車修理業二、F214030汽、機車零件配備零售業三、F214020機車零售業四、F214050車胎零售業五、ZZ99999除許可業務外，得經營法令非禁止或限制之業務",
    "出資額(元)": {
        "林_隆": "20000"
    },
    "url": "\/fts\/query\/QueryBusmDetail\/queryBusmDetail.do?objectId=SEIzMTUzNDgzMDIzMjAwMDAwMDAwMDA3MzAyMzEx&banNo=31534830&banKey=23200000000007302311&disj=DBA070B5A1ACCC8E1D3DB2D9D388FF2C&fhl=zh_TW"
}