{
    "id": "36645976",
    "登記機關": "高雄市政府經濟發展局",
    "核准設立日期": {
        "year": 2006,
        "month": 12,
        "day": 29
    },
    "最近異動日期": {
        "year": 2007,
        "month": 11,
        "day": 19
    },
    "商業名稱": "漂亮寶貝企業行",
    "負責人姓名": "吳_遠",
    "現況": "歇業",
    "資本額(元)": "3,000",
    "組織類型": "獨資",
    "地址": "高雄市鳳山區新興里維新路１５５號２樓（營業所在地僅供辦公連絡用）",
    "營業項目": "1\r\n\r\n                    F102040\r\n\r\n                    飲料批發業\r\n\r\n              \r\n                    2\r\n\r\n                    F102030\r\n\r\n                    菸酒批發業\r\n\r\n              \r\n                    3\r\n\r\n                    F102170\r\n\r\n                    食品什貨批發業\r\n\r\n              \r\n                    4\r\n\r\n                    F109070\r\n\r\n                    文教、樂器、育樂用品批發業"
}