{
    "id": "62985438",
    "登記機關": "高雄市政府",
    "核准設立日期": {
        "year": 2006,
        "month": 10,
        "day": 2
    },
    "最近異動日期": {
        "year": 2022,
        "month": 7,
        "day": 6
    },
    "商業名稱": "晶鳳機電企業社",
    "負責人姓名": "吳_承",
    "現況": "停業\r\n\t\t\t\t\t\t\t\t\t\t\t\t\t\t\r\n\t\t\t\t\t\t\t\t\t\t\t\t\t\t\t(停業起迄日期\r\n\t\t\t\t\t\t\t\t\t\t\t\t\t\t\t111年02月01日\r\n\t\t\t\t\t\t\t\t\t\t\t\t\t\t\t至\r\n\t\t\t\t\t\t\t\t\t\t\t\t\t\t\t112年01月31日)",
    "資本額(元)": "1,000,000",
    "組織類型": "獨資",
    "地址": "高雄市岡山區竹圍里竹圍東街８５號7樓之１０",
    "營業項目": "1\r\n\t\t\t\t\t\t\t\t\t\t\t\t\t\t\tF113010\r\n\t\t\t\t\t\t\t\t\t\t\t\t\t\t\t機械批發業\r\n\t\t\t\t\t\t\t\t\t\t\t\t\t\t\r\n\t\t\t\t\t\t\t\t\t\t\t\t\t\t\t2\r\n\t\t\t\t\t\t\t\t\t\t\t\t\t\t\tF213080\r\n\t\t\t\t\t\t\t\t\t\t\t\t\t\t\t機械器具零售業\r\n\t\t\t\t\t\t\t\t\t\t\t\t\t\t\r\n\t\t\t\t\t\t\t\t\t\t\t\t\t\t\t3\r\n\t\t\t\t\t\t\t\t\t\t\t\t\t\t\tF113020\r\n\t\t\t\t\t\t\t\t\t\t\t\t\t\t\t電器批發業\r\n\t\t\t\t\t\t\t\t\t\t\t\t\t\t\r\n\t\t\t\t\t\t\t\t\t\t\t\t\t\t\t4\r\n\t\t\t\t\t\t\t\t\t\t\t\t\t\t\tF213010\r\n\t\t\t\t\t\t\t\t\t\t\t\t\t\t\t電器零售業\r\n\t\t\t\t\t\t\t\t\t\t\t\t\t\t\r\n\t\t\t\t\t\t\t\t\t\t\t\t\t\t\t5\r\n\t\t\t\t\t\t\t\t\t\t\t\t\t\t\tF106010\r\n\t\t\t\t\t\t\t\t\t\t\t\t\t\t\t五金批發業\r\n\t\t\t\t\t\t\t\t\t\t\t\t\t\t\r\n\t\t\t\t\t\t\t\t\t\t\t\t\t\t\t6\r\n\t\t\t\t\t\t\t\t\t\t\t\t\t\t\tF206010\r\n\t\t\t\t\t\t\t\t\t\t\t\t\t\t\t五金零售業\r\n\t\t\t\t\t\t\t\t\t\t\t\t\t\t\r\n\t\t\t\t\t\t\t\t\t\t\t\t\t\t\t7\r\n\t\t\t\t\t\t\t\t\t\t\t\t\t\t\tE604010\r\n\t\t\t\t\t\t\t\t\t\t\t\t\t\t\t機械安裝業",
    "出資額(元)": {
        "吳_承": "1000000"
    },
    "url": "\/fts\/query\/QueryBusmDetail\/queryBusmDetail.do?objectId=SEI2Mjk4NTQzODUwMjAwMDAwMDAwMDExMzAzNDU3&banNo=62985438&banKey=50200000000011303457&disj=05416DC7AD7D883846D5E2724B9E03FF&fhl=zh_TW"
}