{
    "id": "67811226",
    "登記機關": "屏東縣政府",
    "核准設立日期": {
        "year": 1997,
        "month": 11,
        "day": 24
    },
    "最近異動日期": {
        "year": 2024,
        "month": 5,
        "day": 16
    },
    "商業名稱": "亮水果商行",
    "負責人姓名": "魏_庭",
    "資本額(元)": "3,000",
    "組織類型": "獨資",
    "地址": "屏東縣長治鄉崙上村崑崙路166號",
    "營業項目": "自產蔬□零售業。",
    "出資額(元)": {
        "魏_庭": "3000"
    },
    "url": "\/fts\/query\/QueryBusmDetail\/queryBusmDetail.do?objectId=SEI2NzgxMTIyNjY0MzAwMDAwMDAwMDAwMTE1NDUy&banNo=67811226&banKey=64300000000000115452&disj=A5048D3DCE5C5ADF6785B5BF8F8DE3BB&fhl=zh_TW",
    "登記現況": "核准設立"
}