{
    "id": "67885802",
    "登記機關": "嘉義市政府",
    "核准設立日期": {
        "year": 1998,
        "month": 11,
        "day": 20
    },
    "商業名稱": "蘇活流行館",
    "負責人姓名": "林_鳳",
    "現況": "歇業／撤銷",
    "資本額(元)": "200,000",
    "組織類型": "獨資",
    "地址": "嘉義市西區西榮里中山路４５３號一、二樓",
    "營業項目": "1\n\r\n\t\t\t\t\t\t\tF204110\n\r\n\t\t\t\t\t\t\t布疋、衣著、鞋、帽、傘、服飾品零售業\n\r\n\t\t\t\t\t\t\r\n\t\t\t\t\t\t\t2\n\r\n\t\t\t\t\t\t\tF209060\n\r\n\t\t\t\t\t\t\t文教、樂器、育樂用品零售（賭博性、色情性、電動玩具除外）",
    "出資額(元)": {
        "林_鳳": "200000"
    },
    "異動核准日期": {
        "year": 2018,
        "month": 10,
        "day": 1
    }
}