{
    "id": "13207356",
    "登記機關": "臺南市政府",
    "核准設立日期": {
        "year": 2001,
        "month": 2,
        "day": 1
    },
    "最近異動日期": {
        "year": 2004,
        "month": 9,
        "day": 29
    },
    "商業名稱": "吉鑫泰商行",
    "負責人姓名": "楊_井",
    "現況": "核准設立",
    "資本額(元)": "10,000",
    "組織類型": "獨資",
    "地址": "臺南市鹽水區汫水里50號",
    "營業項目": "1\r\n\t\t\t\t\t\t\t\t\t\t\t\t\t\t\tF101100\r\n\t\t\t\t\t\t\t\t\t\t\t\t\t\t\t花卉批發業",
    "出資額(元)": {
        "楊_井": "10000"
    },
    "url": "\/fts\/query\/QueryBusmDetail\/queryBusmDetail.do?objectId=SEIxMzIwNzM1NjU0MTAwMDAwMDAwMDAwMTQxMjUx&banNo=13207356&banKey=54100000000000141251&disj=F9F981AFE4827DA75A5E33521D491FDF&fhl=zh_TW"
}