{
    "id": "13668527",
    "登記機關": "宜蘭縣政府",
    "核准設立日期": {
        "year": 2002,
        "month": 7,
        "day": 16
    },
    "最近異動日期": {
        "year": 2024,
        "month": 4,
        "day": 1
    },
    "商業名稱": "傳動企業社",
    "負責人姓名": "曾_云",
    "現況": "核准設立",
    "資本額(元)": "10,000",
    "組織類型": "獨資",
    "地址": "宜蘭縣羅東鎮新群里中山路一段７７號一樓",
    "營業項目": "1\r\n\t\t\t\t\t\t\t\t\t\t\t\t\t\t\tF214030\r\n\t\t\t\t\t\t\t\t\t\t\t\t\t\t\t汽、機車零件配備零售業(祇供配件零售不得作修理場所)",
    "出資額(元)": {
        "曾_云": "10000"
    },
    "url": "\/fts\/query\/QueryBusmDetail\/queryBusmDetail.do?objectId=SEIxMzY2ODUyNzQzNDAwMDAwMDAwMDAwMDU2NzEw&banNo=13668527&banKey=43400000000000056710&disj=42F7789B1B7273C8CAA9A2E7BAD22BD6&fhl=zh_TW"
}