{
    "id": "08174974",
    "登記機關": "花蓮縣政府",
    "核准設立日期": {
        "year": 1994,
        "month": 10,
        "day": 4
    },
    "最近異動日期": {
        "year": 2024,
        "month": 10,
        "day": 29
    },
    "商業名稱": "酒久九商號",
    "負責人姓名": "蔣_麗",
    "資本額(元)": "3,000",
    "組織類型": "獨資",
    "地址": "花蓮縣瑞穗鄉奇美村奇美三十一號一樓",
    "營業項目": "菸酒、雜貨買賣",
    "出資額(元)": {
        "蔣_麗": "3000"
    },
    "url": "\/fts\/query\/QueryBusmDetail\/queryBusmDetail.do?objectId=SEIwODE3NDk3NDY0NTAwMDAwMDAwMDAwMDczODQy&banNo=08174974&banKey=64500000000000073842&disj=999570EDE158E6B8857E6297CE348DDD&fhl=zh_TW",
    "登記現況": "歇業"
}