{
    "id": "09321783",
    "登記機關": "苗栗縣政府",
    "核准設立日期": {
        "year": 2006,
        "month": 3,
        "day": 17
    },
    "商業名稱": "榮發工程行",
    "負責人姓名": "張_發",
    "現況": "歇業／撤銷",
    "資本額(元)": "200,000",
    "組織類型": "獨資",
    "地址": "苗栗縣造橋鄉大龍村3鄰石椿臼3號1樓",
    "營業項目": "1\n\r\n\t\t\t\t\t\t\tF111090\n\r\n\t\t\t\t\t\t\t建材批發業〈現場不作堆置棧放〉\n\r\n\t\t\t\t\t\t\r\n\t\t\t\t\t\t\t2\n\r\n\t\t\t\t\t\t\tF106010\n\r\n\t\t\t\t\t\t\t五金批發業〈現場不作堆置棧放〉\n\r\n\t\t\t\t\t\t\r\n\t\t\t\t\t\t\t3\n\r\n\t\t\t\t\t\t\tF211010\n\r\n\t\t\t\t\t\t\t建材零售業〈現場不作堆置棧放〉\n\r\n\t\t\t\t\t\t\r\n\t\t\t\t\t\t\t4\n\r\n\t\t\t\t\t\t\tF206010\n\r\n\t\t\t\t\t\t\t五金零售業〈現場不作堆置棧放〉\n\r\n\t\t\t\t\t\t\r\n\t\t\t\t\t\t\t5\n\r\n\t\t\t\t\t\t\tE901010\n\r\n\t\t\t\t\t\t\t油漆工程業〈至現場作業〉\n\r\n\t\t\t\t\t\t\r\n\t\t\t\t\t\t\t6\n\r\n\t\t\t\t\t\t\tE903010\n\r\n\t\t\t\t\t\t\t防蝕、防銹工程業〈至現場作業〉\n\r\n\t\t\t\t\t\t\r\n\t\t\t\t\t\t\t7\n\r\n\t\t\t\t\t\t\tE603100\n\r\n\t\t\t\t\t\t\t電焊工程業〈至現場作業〉",
    "出資額(元)": {
        "張_發": "200000"
    },
    "異動核准日期": {
        "year": 2018,
        "month": 7,
        "day": 23
    }
}