{
    "id": "09530022",
    "登記機關": "高雄市政府",
    "核准設立日期": {
        "year": 2013,
        "month": 4,
        "day": 26
    },
    "最近異動日期": {
        "year": 2025,
        "month": 1,
        "day": 6
    },
    "商業名稱": "老賈小館",
    "負責人姓名": "賈_賀",
    "資本額(元)": "100,000",
    "組織類型": "獨資",
    "地址": "高雄市鳳山區文化路１４９號１樓",
    "營業項目": "1\r\n\t\t\t\t\t\t\t\t\t\t\t\t\t\t\tF501060\r\n\t\t\t\t\t\t\t\t\t\t\t\t\t\t\t餐館業",
    "出資額(元)": {
        "賈_賀": "100000"
    },
    "url": "\/fts\/query\/QueryBusmDetail\/queryBusmDetail.do?objectId=SEIwOTUzMDAyMjMwMjAwMDAwMDAwMDA5MTI3NDQx&banNo=09530022&banKey=30200000000009127441&disj=97BB597AF25FC963450BA586D827D883&fhl=zh_TW",
    "登記現況": "核准設立"
}