{
    "id": "09773998",
    "登記機關": "新北市政府經濟發展局",
    "核准設立日期": {
        "year": 2006,
        "month": 8,
        "day": 11
    },
    "最近異動日期": {
        "year": 2022,
        "month": 1,
        "day": 11
    },
    "商業名稱": "日安吊車工程行",
    "負責人姓名": "張_芳",
    "現況": "核准設立",
    "資本額(元)": "360,000",
    "組織類型": "獨資",
    "地址": "新北市新店區安泰路60巷29號",
    "營業項目": "1\r\n\t\t\t\t\t\t\t\t\t\t\t\t\t\t\tEZ02010\r\n\t\t\t\t\t\t\t\t\t\t\t\t\t\t\t起重工程業",
    "出資額(元)": {
        "張_芳": "360000"
    },
    "url": "\/fts\/query\/QueryBusmDetail\/queryBusmDetail.do?objectId=SEIwOTc3Mzk5ODQzMTAwMDAwMDAwMDAwNDk2MTIw&banNo=09773998&banKey=43100000000000496120&disj=9E961F3F20A8752B0053669F40D5C572&fhl=zh_TW"
}