{
    "id": "09824504",
    "登記機關": "新北市政府經濟發展局",
    "核准設立日期": {
        "year": 2007,
        "month": 5,
        "day": 1
    },
    "最近異動日期": {
        "year": 2020,
        "month": 9,
        "day": 4
    },
    "商業名稱": "藝沐汽車美容",
    "負責人姓名": "鄭_驊",
    "現況": "核准設立",
    "資本額(元)": "50,000",
    "組織類型": "獨資",
    "地址": "新北市永和區永亨路１０９號",
    "營業項目": "1\r\n\t\t\t\t\t\t\t\t\t\t\t\t\t\t\tJA01990\r\n\t\t\t\t\t\t\t\t\t\t\t\t\t\t\t其他汽車服務業（汽車美容）",
    "出資額(元)": {
        "鄭_驊": "50000"
    },
    "url": "\/fts\/query\/QueryBusmDetail\/queryBusmDetail.do?objectId=SEIwOTgyNDUwNDEzMTAwMDAwMDAwMDAwNTMwNzg3&banNo=09824504&banKey=13100000000000530787&disj=0203889B198DECE5B704044354F19531&fhl=zh_TW"
}