{
    "id": "09830219",
    "登記機關": "桃園市政府",
    "核准設立日期": {
        "year": 2007,
        "month": 5,
        "day": 18
    },
    "最近異動日期": {
        "year": 2023,
        "month": 5,
        "day": 2
    },
    "商業名稱": "鉦泰鋁門窗行",
    "負責人姓名": "游_豐",
    "現況": "歇業",
    "資本額(元)": "250,000",
    "組織類型": "獨資",
    "地址": "桃園市中壢區中原里文化路１５２號１樓",
    "營業項目": "一、Ｆ２１１０１０建材零售業二、Ｆ２９９９９０其他零售業三、Ｅ８０１０２０門窗安裝工程業（赴客戶現場作業）四、Ｆ１９９９９０其他批發業",
    "出資額(元)": {
        "游_豐": "250000"
    },
    "url": "\/fts\/query\/QueryBusmDetail\/queryBusmDetail.do?objectId=SEIwOTgzMDIxOTYzMjAwMDAwMDAwMDAwMzUyMDAy&banNo=09830219&banKey=63200000000000352002&disj=ABAA46E0EEE372764F01FDA75A3FCB04&fhl=zh_TW"
}