{
    "id": "81332079",
    "登記機關": "嘉義縣政府",
    "核准設立日期": {
        "year": 2019,
        "month": 2,
        "day": 12
    },
    "最近異動日期": {
        "year": 2019,
        "month": 10,
        "day": 30
    },
    "商業名稱": "陸帥鞋創事業行",
    "負責人姓名": "陸_華",
    "現況": "歇業",
    "資本額(元)": "8,800",
    "組織類型": "獨資",
    "地址": "嘉義縣民雄鄉文隆村13鄰建國路二段167-10號1樓",
    "營業項目": "1\r\n\t\t\t\t\t\t\t\t\t\t\t\t\t\t\tI599990\r\n\t\t\t\t\t\t\t\t\t\t\t\t\t\t\t其他設計業\r\n\t\t\t\t\t\t\t\t\t\t\t\t\t\t\r\n\t\t\t\t\t\t\t\t\t\t\t\t\t\t\t2\r\n\t\t\t\t\t\t\t\t\t\t\t\t\t\t\tF399040\r\n\t\t\t\t\t\t\t\t\t\t\t\t\t\t\t無店面零售業",
    "出資額(元)": {
        "陸_華": "8800"
    },
    "url": "\/fts\/query\/QueryBusmDetail\/queryBusmDetail.do?objectId=SEI4MTMzMjA3OTQ0MDAwMDAwMDAwMDE2NTQyOTc1&banNo=81332079&banKey=44000000000016542975"
}