{
    "id": "81803465",
    "登記機關": "基隆市政府",
    "核准設立日期": {
        "year": 1994,
        "month": 1,
        "day": 20
    },
    "最近異動日期": {
        "year": 2021,
        "month": 2,
        "day": 19
    },
    "商業名稱": "和樂電子遊戲場業",
    "負責人姓名": "王_秀",
    "現況": "核准設立",
    "資本額(元)": "50,000",
    "組織類型": "獨資",
    "地址": "基隆市仁愛區文昌里忠二路五六號",
    "營業項目": "1\r\n\t\t\t\t\t\t\t\t\t\t\t\t\t\t\tJ701010\r\n\t\t\t\t\t\t\t\t\t\t\t\t\t\t\t電子遊戲場業<限制級>",
    "出資額(元)": {
        "王_秀": "50000"
    },
    "url": "\/fts\/query\/QueryBusmDetail\/queryBusmDetail.do?objectId=SEI4MTgwMzQ2NTQxMTAwMDAwMDAwMDAwMDUwNDYw&banNo=81803465&banKey=41100000000000050460&disj=F676C9A3AD6DC9694337FF8C3194ACFD&fhl=zh_TW"
}