{
    "id": "81867410",
    "登記機關": "高雄市政府",
    "核准設立日期": {
        "year": 1994,
        "month": 5,
        "day": 26
    },
    "最近異動日期": {
        "year": 2021,
        "month": 6,
        "day": 1
    },
    "商業名稱": "翔旺當舖",
    "負責人姓名": "張_之",
    "現況": "核准設立",
    "資本額(元)": "1,500,000",
    "組織類型": "獨資",
    "地址": "高雄市鳳山區鳳林路282號1樓",
    "營業項目": "一當舖業．本案營業場所僅限於地面建築物之第壹層，但不得經營足以發生噪音、震動、特殊氣味、污染或有礙居住安寧、公共安全之建築物或土地之使用。",
    "出資額(元)": {
        "張_之": "1500000"
    },
    "url": "\/fts\/query\/QueryBusmDetail\/queryBusmDetail.do?objectId=SEI4MTg2NzQxMDkwMjAwMDAwMDAwMDAwMTk2NzE1&banNo=81867410&banKey=90200000000000196715&disj=7342AB5A62B7F0CEB6AADC932EBC452C&fhl=zh_TW"
}