{
    "id": "82144309",
    "登記機關": "新北市政府經濟發展局",
    "核准設立日期": {
        "year": 2018,
        "month": 11,
        "day": 13
    },
    "最近異動日期": {
        "year": 2023,
        "month": 11,
        "day": 27
    },
    "商業名稱": "一六三複合式餐坊",
    "負責人姓名": "余_仙",
    "現況": "核准設立",
    "資本額(元)": "100,000",
    "組織類型": "獨資",
    "地址": "新北市新店區光明街163號(1樓)",
    "營業項目": "1\r\n\t\t\t\t\t\t\t\t\t\t\t\t\t\t\tF501060\r\n\t\t\t\t\t\t\t\t\t\t\t\t\t\t\t餐館業\r\n\t\t\t\t\t\t\t\t\t\t\t\t\t\t\r\n\t\t\t\t\t\t\t\t\t\t\t\t\t\t\t2\r\n\t\t\t\t\t\t\t\t\t\t\t\t\t\t\tF203020\r\n\t\t\t\t\t\t\t\t\t\t\t\t\t\t\t菸酒零售業",
    "出資額(元)": {
        "余_仙": "100000"
    },
    "url": "\/fts\/query\/QueryBusmDetail\/queryBusmDetail.do?objectId=SEI4MjE0NDMwOTEzMTAwMDAwMDAwMDE2MjQ3MTg1&banNo=82144309&banKey=13100000000016247185&disj=C14924BB3CD92BF9A47073A92F142309&fhl=zh_TW"
}