{
    "id": "85250859",
    "登記機關": "桃園市政府",
    "核准設立日期": {
        "year": 2019,
        "month": 11,
        "day": 8
    },
    "最近異動日期": {
        "year": 2024,
        "month": 12,
        "day": 25
    },
    "商業名稱": "新風格美髮院",
    "負責人姓名": "吳_青",
    "資本額(元)": "150,000",
    "組織類型": "獨資",
    "地址": "桃園市平鎮區南勢里中豐路南勢二段149號(1樓)",
    "營業項目": "一、JZ99080美容美髮服務業二、F208040化粧品零售業",
    "出資額(元)": {
        "吳_青": "150000"
    },
    "url": "\/fts\/query\/QueryBusmDetail\/queryBusmDetail.do?objectId=SEI4NTI1MDg1OTczMjAwMDAwMDAwMDE3NTAwMjIx&banNo=85250859&banKey=73200000000017500221&disj=3788CE827E4666468D607F7CDFCC9F34&fhl=zh_TW",
    "登記現況": "歇業"
}