{
    "id": "85611024",
    "登記機關": "臺南市政府",
    "核准設立日期": {
        "year": 2020,
        "month": 6,
        "day": 5
    },
    "最近異動日期": {
        "year": 2022,
        "month": 9,
        "day": 12
    },
    "商業名稱": "福神企業社",
    "負責人姓名": "顏_霖",
    "現況": "歇業",
    "資本額(元)": "200,000",
    "組織類型": "合夥",
    "地址": "臺南市北區力行里開南街275巷8弄2號1樓",
    "營業項目": "1\r\n\t\t\t\t\t\t\t\t\t\t\t\t\t\t\tF101050\r\n\t\t\t\t\t\t\t\t\t\t\t\t\t\t\t水產品批發業\r\n\t\t\t\t\t\t\t\t\t\t\t\t\t\t\r\n\t\t\t\t\t\t\t\t\t\t\t\t\t\t\t2\r\n\t\t\t\t\t\t\t\t\t\t\t\t\t\t\tF101040\r\n\t\t\t\t\t\t\t\t\t\t\t\t\t\t\t家畜家禽批發業\r\n\t\t\t\t\t\t\t\t\t\t\t\t\t\t\r\n\t\t\t\t\t\t\t\t\t\t\t\t\t\t\t3\r\n\t\t\t\t\t\t\t\t\t\t\t\t\t\t\tF101130\r\n\t\t\t\t\t\t\t\t\t\t\t\t\t\t\t蔬果批發業\r\n\t\t\t\t\t\t\t\t\t\t\t\t\t\t\r\n\t\t\t\t\t\t\t\t\t\t\t\t\t\t\t4\r\n\t\t\t\t\t\t\t\t\t\t\t\t\t\t\tF101990\r\n\t\t\t\t\t\t\t\t\t\t\t\t\t\t\t其他農、畜、水產品批發業\r\n\t\t\t\t\t\t\t\t\t\t\t\t\t\t\r\n\t\t\t\t\t\t\t\t\t\t\t\t\t\t\t5\r\n\t\t\t\t\t\t\t\t\t\t\t\t\t\t\tF399040\r\n\t\t\t\t\t\t\t\t\t\t\t\t\t\t\t無店面零售業\r\n\t\t\t\t\t\t\t\t\t\t\t\t\t\t\r\n\t\t\t\t\t\t\t\t\t\t\t\t\t\t\t6\r\n\t\t\t\t\t\t\t\t\t\t\t\t\t\t\tF401010\r\n\t\t\t\t\t\t\t\t\t\t\t\t\t\t\t國際貿易業",
    "合夥人姓名": "林桓宇",
    "出資額(元)": {
        "顏_霖": "100000",
        "林_宇": "100000"
    },
    "url": "\/fts\/query\/QueryBusmDetail\/queryBusmDetail.do?objectId=SEI4NTYxMTAyNDYyMTAwMDAwMDAwMDE4MzAwMTMy&banNo=85611024&banKey=62100000000018300132&disj=3950AE99969BE69D9BF2FA42C649E10D&fhl=zh_TW"
}