{
    "id": "85786234",
    "登記機關": "嘉義縣政府",
    "核准設立日期": {
        "year": 2021,
        "month": 9,
        "day": 23
    },
    "最近異動日期": {
        "year": 2024,
        "month": 10,
        "day": 11
    },
    "商業名稱": "大立工程行",
    "負責人姓名": "葉_偉",
    "資本額(元)": "1,000,000",
    "組織類型": "獨資",
    "地址": "嘉義縣水上鄉柳林村柳子林50之63號一樓",
    "營業項目": "1\r\n\t\t\t\t\t\t\t\t\t\t\t\t\t\t\tEZ99990\r\n\t\t\t\t\t\t\t\t\t\t\t\t\t\t\t其他工程業\r\n\t\t\t\t\t\t\t\t\t\t\t\t\t\t\r\n\t\t\t\t\t\t\t\t\t\t\t\t\t\t\t2\r\n\t\t\t\t\t\t\t\t\t\t\t\t\t\t\tE601010\r\n\t\t\t\t\t\t\t\t\t\t\t\t\t\t\t電器承裝業\r\n\t\t\t\t\t\t\t\t\t\t\t\t\t\t\r\n\t\t\t\t\t\t\t\t\t\t\t\t\t\t\t3\r\n\t\t\t\t\t\t\t\t\t\t\t\t\t\t\tF111090\r\n\t\t\t\t\t\t\t\t\t\t\t\t\t\t\t建材批發業\r\n\t\t\t\t\t\t\t\t\t\t\t\t\t\t\r\n\t\t\t\t\t\t\t\t\t\t\t\t\t\t\t4\r\n\t\t\t\t\t\t\t\t\t\t\t\t\t\t\tZZ99999\r\n\t\t\t\t\t\t\t\t\t\t\t\t\t\t\t除許可業務外，得經營法令非禁止或限制之業務",
    "出資額(元)": {
        "葉_偉": "1000000"
    },
    "url": "\/fts\/query\/QueryBusmDetail\/queryBusmDetail.do?objectId=SEI4NTc4NjIzNDg0MDAwMDAwMDAwMDIwMjczMjI4&banNo=85786234&banKey=84000000000020273228&disj=4CF64B5F78ADD743BF4CACF5B79220B2&fhl=zh_TW",
    "登記現況": "核准設立"
}