{
    "id": "87477591",
    "登記機關": "新北市政府經濟發展局",
    "核准設立日期": {
        "year": 2020,
        "month": 11,
        "day": 30
    },
    "最近異動日期": {
        "year": 2022,
        "month": 5,
        "day": 2
    },
    "商業名稱": "暖心天地居家工作室",
    "負責人姓名": "尤_志",
    "現況": "歇業",
    "資本額(元)": "100,000",
    "組織類型": "獨資",
    "地址": "新北市汐止區汐萬路2段228巷31弄171號4樓",
    "營業項目": "1\r\n\t\t\t\t\t\t\t\t\t\t\t\t\t\t\tIZ12010\r\n\t\t\t\t\t\t\t\t\t\t\t\t\t\t\t人力派遣業\r\n\t\t\t\t\t\t\t\t\t\t\t\t\t\t\r\n\t\t\t\t\t\t\t\t\t\t\t\t\t\t\t2\r\n\t\t\t\t\t\t\t\t\t\t\t\t\t\t\tJ101010\r\n\t\t\t\t\t\t\t\t\t\t\t\t\t\t\t建築物清潔服務業",
    "出資額(元)": {
        "尤_志": "100000"
    },
    "url": "\/fts\/query\/QueryBusmDetail\/queryBusmDetail.do?objectId=SEI4NzQ3NzU5MTEzMTAwMDAwMDAwMDE5MDY5MjAz&banNo=87477591&banKey=13100000000019069203&disj=88D5473A3F3B0D144C51A9901A8E1F4B&fhl=zh_TW"
}