{
    "id": "88413569",
    "登記機關": "臺中市政府",
    "核准設立日期": {
        "year": 2024,
        "month": 8,
        "day": 5
    },
    "最近異動日期": {
        "year": 2024,
        "month": 10,
        "day": 8
    },
    "商業名稱": "哇哈妮工作室",
    "負責人姓名": "宋_恩",
    "資本額(元)": "100,000",
    "組織類型": "獨資",
    "地址": "臺中市和平區平等里中興路三段環山三巷23之2號1樓",
    "營業項目": "1\r\n\t\t\t\t\t\t\t\t\t\t\t\t\t\t\tF201010\r\n\t\t\t\t\t\t\t\t\t\t\t\t\t\t\t農產品零售業\r\n\t\t\t\t\t\t\t\t\t\t\t\t\t\t\r\n\t\t\t\t\t\t\t\t\t\t\t\t\t\t\t2\r\n\t\t\t\t\t\t\t\t\t\t\t\t\t\t\tF399040\r\n\t\t\t\t\t\t\t\t\t\t\t\t\t\t\t無店面零售業\r\n\t\t\t\t\t\t\t\t\t\t\t\t\t\t\r\n\t\t\t\t\t\t\t\t\t\t\t\t\t\t\t3\r\n\t\t\t\t\t\t\t\t\t\t\t\t\t\t\tA101020\r\n\t\t\t\t\t\t\t\t\t\t\t\t\t\t\t農作物栽培業",
    "出資額(元)": {
        "宋_恩": "100000"
    },
    "url": "\/fts\/query\/QueryBusmDetail\/queryBusmDetail.do?objectId=SEI4ODQxMzU2OTMxNzAwMDAwMDAwMDI0NjMwMjc2&banNo=88413569&banKey=31700000000024630276&disj=FE4BFB2C649A533A76B5458E54D42464&fhl=zh_TW",
    "登記現況": "核准設立"
}