{
    "id": "88952307",
    "登記機關": "屏東縣政府",
    "核准設立日期": {
        "year": 2022,
        "month": 7,
        "day": 4
    },
    "最近異動日期": {
        "year": 2022,
        "month": 7,
        "day": 4
    },
    "商業名稱": "同心汽車商行",
    "負責人姓名": "張_萍",
    "現況": "核准設立",
    "資本額(元)": "200,000",
    "組織類型": "獨資",
    "地址": "屏東縣屏東市華二街１４號",
    "營業項目": "1\r\n\t\t\t\t\t\t\t\t\t\t\t\t\t\t\tF214010\r\n\t\t\t\t\t\t\t\t\t\t\t\t\t\t\t汽車零售業\r\n\t\t\t\t\t\t\t\t\t\t\t\t\t\t\r\n\t\t\t\t\t\t\t\t\t\t\t\t\t\t\t2\r\n\t\t\t\t\t\t\t\t\t\t\t\t\t\t\tF214030\r\n\t\t\t\t\t\t\t\t\t\t\t\t\t\t\t汽、機車零件配備零售業\r\n\t\t\t\t\t\t\t\t\t\t\t\t\t\t\r\n\t\t\t\t\t\t\t\t\t\t\t\t\t\t\t3\r\n\t\t\t\t\t\t\t\t\t\t\t\t\t\t\tZZ99999\r\n\t\t\t\t\t\t\t\t\t\t\t\t\t\t\t除許可業務外，得經營法令非禁止或限制之業務",
    "出資額(元)": {
        "張_萍": "200000"
    },
    "url": "\/fts\/query\/QueryBusmDetail\/queryBusmDetail.do?objectId=SEI4ODk1MjMwNzI0MzAwMDAwMDAwMDIxNDIwNTMy&banNo=88952307&banKey=24300000000021420532&disj=2C5DBBB253266F62EAC7F6EF6DCA568E&fhl=zh_TW"
}