{
    "id": "52726074",
    "登記機關": "臺中市政府",
    "核准設立日期": {
        "year": 1911,
        "month": 0,
        "day": 0
    },
    "最近異動日期": {
        "year": 2023,
        "month": 2,
        "day": 17
    },
    "商業名稱": "進億肉舖",
    "負責人姓名": "許_育",
    "現況": "歇業",
    "資本額(元)": "45,000",
    "組織類型": "獨資",
    "地址": "臺中市北屯區北興里三光巷９０弄５７之８號一樓",
    "營業項目": "獸肉買賣業．( 屠宰商，買賣行為於市場為之 )( 營址限辦公室使用 )(本案依本市非供公眾使用建築物營利事業登記房屋證明暫行作業規定辦理)( 上開業務之經營應遵照有關法令規定辦理 )( 以下空白 )",
    "出資額(元)": {
        "許_育": "45000"
    },
    "url": "\/fts\/query\/QueryBusmDetail\/queryBusmDetail.do?objectId=SEI1MjcyNjA3NDgxNzAwMDAwMDAwMDAwMTQ1MTY0&banNo=52726074&banKey=81700000000000145164&disj=19770B44A0B57669E46CED2458C53700&fhl=zh_TW"
}