{
    "id": "25252072",
    "登記機關": "臺中市政府",
    "核准設立日期": {
        "year": 2010,
        "month": 5,
        "day": 10
    },
    "最近異動日期": {
        "year": 2015,
        "month": 11,
        "day": 5
    },
    "商業名稱": "洗新革面企業社",
    "負責人姓名": "李_輝",
    "現況": "歇業",
    "資本額(元)": "240,000",
    "組織類型": "獨資",
    "地址": "臺中市沙鹿區埔子里明秀一街113號",
    "營業項目": "1\r\n\r\n\t\t\t\t\t\t\tJZ99990\r\n\r\n\t\t\t\t\t\t\t未分類其他服務業\r\n\r\n\t\t\t\t\t\t\r\n\t\t\t\t\t\t\t2\r\n\r\n\t\t\t\t\t\t\tJA03010\r\n\r\n\t\t\t\t\t\t\t洗衣業"
}