{
    "id": "26561532",
    "登記機關": "基隆市政府",
    "核准設立日期": {
        "year": 2011,
        "month": 6,
        "day": 9
    },
    "最近異動日期": {
        "year": 2022,
        "month": 9,
        "day": 6
    },
    "商業名稱": "參捌咖啡店",
    "負責人姓名": "余_蓁",
    "現況": "核准設立",
    "資本額(元)": "20,000",
    "組織類型": "獨資",
    "地址": "基隆市仁愛區孝三路38號1樓",
    "營業項目": "1\r\n\t\t\t\t\t\t\t\t\t\t\t\t\t\t\tF501030\r\n\t\t\t\t\t\t\t\t\t\t\t\t\t\t\t飲料店業",
    "出資額(元)": {
        "余_蓁": "20000"
    },
    "url": "\/fts\/query\/QueryBusmDetail\/queryBusmDetail.do?objectId=SEIyNjU2MTUzMjUxMTAwMDAwMDAwMDA2OTY1MTY3&banNo=26561532&banKey=51100000000006965167&disj=0091C4FA5D7D64FAFB24BD75BDE4709B&fhl=zh_TW"
}