{
    "id": "26630741",
    "登記機關": "桃園市政府",
    "核准設立日期": {
        "year": 2011,
        "month": 9,
        "day": 7
    },
    "最近異動日期": {
        "year": 2022,
        "month": 11,
        "day": 30
    },
    "商業名稱": "麗群理髮店",
    "負責人姓名": "林_鳴",
    "現況": "核准設立",
    "資本額(元)": "30,000",
    "組織類型": "獨資",
    "地址": "桃園市桃園區福林里長沙街52號1、2樓",
    "營業項目": "一、JZ99080美容美髮服務業二、JZ99110瘦身美容業",
    "出資額(元)": {
        "林_鳴": "30000"
    },
    "url": "\/fts\/query\/QueryBusmDetail\/queryBusmDetail.do?objectId=SEIyNjYzMDc0MTgzMjAwMDAwMDAwMDA3MjYwOTgz&banNo=26630741&banKey=83200000000007260983&disj=638BCD13A81376568ECF5B9DF752068B&fhl=zh_TW"
}